module/__init__.py
module/analysis.py
module/compute.py
module/get.py
module/output.py
dualnet_tcm-0.1a8.dist-info/LICENSE
dualnet_tcm-0.1a8.dist-info/METADATA
dualnet_tcm-0.1a8.dist-info/WHEEL
dualnet_tcm-0.1a8.dist-info/top_level.txt
dualnet_tcm-0.1a8.dist-info/RECORD
