Metadata-Version: 2.2
Name: DualNet-TCM
Version: 0.1a8
Summary: DualNet-TCM：分别从中医和西医维度对中药进行“以靶找药”和“以药找靶”的新型中药网络药理学
Home-page: https://github.com/MLi-lab-Bioinformatics-NJUCM/HerbiV
Author: 沈天威、胡屹莹
Author-email: 2990834217@qq.com
Project-URL: Bug Reports, https://github.com/Carrie-HuYY/DualNet-TCM/issues
Project-URL: Source, https://github.com/Carrie-HuYY/DualNet-TCM
Keywords: network pharmacology
Classifier: Programming Language :: Python :: 3
Classifier: License :: OSI Approved :: MIT License
Classifier: Operating System :: OS Independent
Classifier: Development Status :: 3 - Alpha
Classifier: Intended Audience :: Healthcare Industry
Classifier: Intended Audience :: Science/Research
Classifier: Natural Language :: Chinese (Simplified)
Classifier: Natural Language :: English
Classifier: Topic :: Scientific/Engineering :: Bio-Informatics
Classifier: Topic :: Scientific/Engineering :: Information Analysis
Requires-Python: >=3.9
License-File: LICENSE
Requires-Dist: numpy
Requires-Dist: pandas
Requires-Dist: tqdm
Requires-Dist: pyecharts
Dynamic: author
Dynamic: author-email
Dynamic: classifier
Dynamic: description
Dynamic: description-content-type
Dynamic: home-page
Dynamic: keywords
Dynamic: project-url
Dynamic: requires-dist
Dynamic: requires-python
Dynamic: summary
